LICENSE
README.rst
setup.py
nlptasks/__init__.py
nlptasks/depchild.py
nlptasks/dephead.py
nlptasks/deptree.py
nlptasks/lemma.py
nlptasks/meta.py
nlptasks/ner.py
nlptasks/ner2.py
nlptasks/padding.py
nlptasks/pos.py
nlptasks/pos2.py
nlptasks/sbd.py
nlptasks/testdata.py
nlptasks/token.py
nlptasks/vocab.py
nlptasks.egg-info/PKG-INFO
nlptasks.egg-info/SOURCES.txt
nlptasks.egg-info/dependency_links.txt
nlptasks.egg-info/requires.txt
nlptasks.egg-info/top_level.txt
nlptasks.egg-info/zip-safe
scripts/nlptasks_downloader.py
test/test_data.py
test/test_depchild.py
test/test_dephead.py
test/test_deptree.py
test/test_lemma.py
test/test_ner.py
test/test_ner2.py
test/test_pos.py
test/test_pos2.py
test/test_sbd.py
test/test_token.py
test/test_vocab.py