Metadata-Version: 1.2
Name: nlptasks
Version: 0.3.2
Summary: Boilerplate code to wrap different libs for NLP tasks.
Home-page: http://github.com/ulf1/nlptasks
Author: Ulf Hamster
Author-email: 554c46@gmail.com
License: Apache License 2.0
Platform: UNKNOWN
Requires-Python: >=3.6
